generate/__init__.py
generate/__main__.py
generate/folder.py
generate/nodes.py
generate/parser.py
generate/py.typed
generate/substitute.py
qr_generate-0.1.2.dist-info/LICENSE
qr_generate-0.1.2.dist-info/METADATA
qr_generate-0.1.2.dist-info/WHEEL
qr_generate-0.1.2.dist-info/top_level.txt
qr_generate-0.1.2.dist-info/RECORD
