Metadata-Version: 2.2
Name: qr-generate
Version: 0.1.2
Summary: generate files from templates
Author-email: Matthew Scroggs <generate@mscroggs.co.uk>
License: MIT License
Project-URL: homepage, https://github.com/quadraturerules/generate
Project-URL: repository, https://github.com/quadraturerules/generate
Requires-Python: >=3.8.0
License-File: LICENSE
Requires-Dist: pyyaml
Provides-Extra: style
Requires-Dist: ruff; extra == "style"
Requires-Dist: mypy; extra == "style"
Provides-Extra: test
Requires-Dist: pytest; extra == "test"
Provides-Extra: ci
Requires-Dist: qr-generate[style,test]; extra == "ci"
